swiss_weatherdata/__init__.py
swiss_weatherdata/gbm.py
swiss_weatherdata-0.0.3.dist-info/METADATA
swiss_weatherdata-0.0.3.dist-info/WHEEL
swiss_weatherdata-0.0.3.dist-info/licenses/LICENSE
swiss_weatherdata-0.0.3.dist-info/RECORD
