Metadata-Version: 2.4
Name: swiss-weatherdata
Version: 0.0.3
Summary: An API to easily download open access weather recordings from MeteoSwiss
Project-URL: Homepage, https://github.com/ptitmatheux/swiss_weatherdata
Project-URL: Issues, https://github.com/ptitmatheux/swiss_weatherdata/issues
Author-email: Michel Matter <mich1983mat@gmail.com>
License-Expression: MIT
License-File: LICENSE
Classifier: Operating System :: OS Independent
Classifier: Programming Language :: Python :: 3
Requires-Python: >=3.9
Requires-Dist: pandas>=2.2.3
